{"cameraMode":{"drawMode":3,"name":"Shadow Cascades","section":"Miscellaneous"},"sceneLighting":true,"audioPlay":false,"sceneViewState":{"m_AlwaysRefresh":false,"showFog":true,"showSkybox":true,"showFlares":true,"showImageEffects":true,"showParticleSystems":true,"showVisualEffectGraphs":true,"m_FxEnabled":true},"in2DMode":false,"pivot":{"x":-1.3748533725738526,"y":3.5,"z":-12.19997787475586},"rotation":{"x":-0.24944598972797395,"y":0.31718164682388308,"z":-0.08686462789773941,"w":-0.9108392000198364},"size":12.12435531616211,"orthographic":false}